mdpd/__init__.py
mdpd/utils.py
mdpd/version.py
mdpd-0.2.0.dist-info/LICENSE
mdpd-0.2.0.dist-info/METADATA
mdpd-0.2.0.dist-info/WHEEL
mdpd-0.2.0.dist-info/RECORD
