Metadata-Version: 2.1
Name: mdpd
Version: 0.2.0
Summary: a simpler tool for convert markdown table to pandas
Home-page: https://github.com/kyoto7250/mdpd
Author: kyoto7250
Author-email: 50972773+kyoto7250@users.noreply.github.com
Requires-Python: >=3.9,<3.13
Classifier: Programming Language :: Python :: 3
Classifier: Programming Language :: Python :: 3.9
Classifier: Programming Language :: Python :: 3.10
Classifier: Programming Language :: Python :: 3.11
Requires-Dist: pandas (>=2.1.1,<3.0.0)
Project-URL: Repository, https://github.com/kyoto7250/mdpd
